psprop/__init__.py
psprop/propagation.py
psprop-0.1.1.dist-info/LICENSE
psprop-0.1.1.dist-info/METADATA
psprop-0.1.1.dist-info/WHEEL
psprop-0.1.1.dist-info/top_level.txt
psprop-0.1.1.dist-info/RECORD
